indian_stock_markets/__init__.py
indian_stock_markets/nse/__init__.py
indian_stock_markets/nse/bhavcopy.py
indian_stock_markets/nse/futstk.py
indian_stock_markets/nse/nse.py
indian_stock_markets/nse/nse.sql
tests/__init__.py
tests/test_bhavcopy.py
tests/test_futstk.py
tests/test_nse.py
indian_stock_markets-0.0.6.dist-info/LICENSE
indian_stock_markets-0.0.6.dist-info/METADATA
indian_stock_markets-0.0.6.dist-info/WHEEL
indian_stock_markets-0.0.6.dist-info/top_level.txt
indian_stock_markets-0.0.6.dist-info/RECORD
