Metadata-Version: 2.1
Name: indian-stock-markets
Version: 0.0.6
Summary: A Python package for analyzing Indian Stock Markets
Home-page: https://github.com/vijayshinva/Indian-Stock-Markets
Author: Vijayshinva B Karnure
Author-email: vijayshinva@outlook.com
License: UNKNOWN
Platform: UNKNOWN
Classifier: Programming Language :: Python :: 3
Classifier: License :: OSI Approved :: Apache Software License
Classifier: Operating System :: OS Independent
Requires-Python: >=3.6
Requires-Dist: requests
Requires-Dist: pandas
